<?xml version="1.0" encoding="UTF-8"?>
<Systems>
<ssys name="Delta Pavonis">
<pos>
<x>15</x>
<y>8</y>
</pos>
<general>
<stars>500</stars>
<asteroids>0</asteroids>
<interference>0</interference>
</general>
<planets>
<planet>Caladan</planet>
</planets>
<fleets>
<fleet chance="100">Test</fleet>
<fleet chance="60">Pirate Hyena</fleet>
<fleet chance="60">Merchant Llama</fleet>
<fleet chance="50">Merchant Mule</fleet>
<fleet chance="40">Merchant Llama</fleet>
<fleet chance="50">Sml Merchant Convoy</fleet>
<fleet chance="40">Sml Merchant Convoy</fleet>
</fleets>
<jumps>
<jump>NCG-7291</jump>
<jump>Arrakis</jump>
</jumps>
</ssys>
<ssys name="Arrakis">
<pos>
<x>47</x>
<y>33</y>
</pos>
<general>
<stars>27</stars>
<asteroids>0</asteroids>
<interference>0</interference>
</general>
<planets>
<planet>Dune</planet>
</planets>
<fleets>
<fleet chance="80">Merchant Llama</fleet>
<fleet chance="60">Merchant Mule</fleet>
<fleet chance="60">Merchant Llama</fleet>
</fleets>
<jumps>
<jump>NCG-7291</jump>
<jump>Delta Pavonis</jump>
</jumps>
</ssys>
<ssys name="NCG-7291">
<pos>
<x>-23</x>
<y>24</y>
</pos>
<general>
<stars>230</stars>
<asteroids>0</asteroids>
<interference>0</interference>
</general>
<planets>
</planets>
<fleets>
<fleet chance="80">Merchant Llama</fleet>
<fleet chance="60">Merchant Mule</fleet>
<fleet chance="60">Pirate Hyena</fleet>
<fleet chance="60">Pirate Hyena</fleet>
</fleets>
<jumps>
<jump>Arrakis</jump>
<jump>Delta Pavonis</jump>
</jumps>
</ssys>
</Systems>
