<?xml version="1.0" encoding="UTF-8"?>
<outfit name="Tricon Centaur Mk8 Engine">
 <general>
  <typename>Core Systems</typename>
  <slot prop="engines">structure</slot>
  <size>medium</size>
  <mass>10</mass>
  <price>3000000</price>
  <description>Tricon's Centaur Mk8 is the state of the art in ship propulsion technology. It bests even the mighty Centaur Mk7.</description>
  <gfx_store>afterburner</gfx_store>
 </general>
 <specific type="modification">
  <thrust>190</thrust>
  <turn>120</turn>
  <speed>200</speed>
  <fuel>800</fuel>
  <energy_regen>-27</energy_regen>
  <engine_limit>1000</engine_limit>
 </specific>
</outfit>
