<outfit name="Unicorp D-23 Medium Plating">
 <general>
  <shortname>U. D-23 Medium Plating</shortname>
  <typename>Core Systems (Hull)</typename>
  <slot prop_extra="hull_secondary" prop="hull">structure</slot>
  <size>medium</size>
  <price>40000</price>
  <description>D-23 plating provides a serviceable layer of armour to medium ships, and doesn't weigh too much.</description>
  <gfx_store>base_hull_m</gfx_store>
  <priority>3</priority>
 </general>
 <specific type="modification">
  <lua_inline>
   require('outfits.lib.multicore').init({
      {'mass', 100, 120},
      {'cargo', 35, 15},
      {'absorb', 55, 14},
      {'armour', 220, 250},
   })
  </lua_inline>
 </specific>
 <tags>
  <tag>core</tag>
 </tags>
</outfit>
