<?xml version='1.0' encoding='UTF-8'?>
<ship name="Dvaered Retribution">
 <lua>dvaered.lua</lua>
 <points>150</points>
 <base_type>Retribution</base_type>
 <gfx size="128" sx="12" sy="12">retribution_dvaered</gfx>
 <rarity>2</rarity>
 <sound>engine</sound>
 <class>Cruiser</class>
 <price>5000000</price>
 <time_mod>1.375</time_mod>
 <trail_generator x="-44" y="20" h="0">fire</trail_generator>
 <trail_generator x="-44" y="-20" h="0">fire</trail_generator>
 <trail_generator x="-28" y="32" h="0">nebula</trail_generator>
 <trail_generator x="-28" y="-32" h="0">nebula</trail_generator>
 <fabricator>House Dvaered</fabricator>
 <license>Heavy Combat Vessel</license>
 <cond>faction.playerStanding("Dvaered") &gt;= 60</cond>
 <condstr>You need at least 60 reputation with House Dvaered.</condstr>
 <description>When the Empire replaced their ageing cruisers with the new Hawking class House Dvaered seized the opportunity to acquire the license for the cruiser and most of the remaining ships. Dvaered engineers reinforced the armor and redesigned the ship's structure while also attaching additional weapon hard points. Afterwards, the ship was renamed to Retribution. However, the electronics remained outdated.</description>
 <health>
  <armour>1800</armour>
  <armour_regen>0</armour_regen>
 </health>
 <characteristics>
  <crew>39</crew>
  <mass>1300</mass>
  <fuel_consumption>400</fuel_consumption>
  <cargo>100</cargo>
 </characteristics>
 <slots>
  <weapon size="large" x="44" y="24" h="0" />
  <weapon size="large" x="44" y="-24" h="0" />
  <weapon size="large" x="10" y="24" h="4" />
  <weapon size="large" x="10" y="-24" h="4" />
  <weapon size="large" prop="fighter_bay" x="-45" y="6" h="4" />
  <weapon size="large" prop="fighter_bay" x="-45" y="-6" h="4" />
  <utility size="large" prop="systems">Unicorp PT-2200 Core System</utility>
  <utility size="large" prop="accessory" />
  <utility size="large" />
  <utility size="large" />
  <utility size="large" />
  <structure size="large" prop="engines">Nexus Bolt 3000 Engine</structure>
  <structure size="large" prop="hull">Unicorp D-58 Heavy Plating</structure>
  <structure size="large" />
  <structure size="large" />
  <structure size="large" />
  <structure size="large" />
  <structure size="large" />
 </slots>
 <stats>
  <speed_mod>-15</speed_mod>
  <armour_mod>20</armour_mod>
  <energy_mod>20</energy_mod>
  <energy_regen_mod>-10</energy_regen_mod>
  <fwd_heat>10</fwd_heat>
  <fwd_damage>20</fwd_damage>
  <fwd_energy>10</fwd_energy>
  <engine_limit_rel>15</engine_limit_rel>
 </stats>
 <tags>
  <tag>dvaered</tag>
 </tags>
</ship>
