<?xml version="1.0" encoding="UTF-8"?>
<outfit name="Unicorp B-12 Medium Plating">
 <general>
  <typename>Core Systems</typename>
  <slot prop="hull">structure</slot>
  <size>medium</size>
  <mass>280</mass>
  <price>200000</price>
  <description>C-8 Plating is similar to D-8 Plating, but the armour plates are furnished with an additional protective layer, increasing both mass and armour.</description>
  <gfx_store>nanobond</gfx_store>
 </general>
 <specific type="modification">
  <cargo>40</cargo>
  <absorb>20</absorb>
  <armour>550</armour>
  <armour_regen>0</armour_regen>
  <ew_hide>0</ew_hide>
 </specific>
</outfit>
