<?xml version="1.0" encoding="UTF-8"?>
<outfit name="Unicorp B-16 Heavy Plating">
 <general>
  <typename>Core Systems</typename>
  <slot prop="hull">structure</slot>
  <size>large</size>
  <mass>3000</mass>
  <price>7000000</price>
  <description>B-16 plating is a low-end heavy punishment hull modification. It is designed to absorb lots of damage, but its armour-to-weight ratio is worse than the C or D variants.</description>
  <gfx_store>nanobond</gfx_store>
 </general>
 <specific type="modification">
  <cargo>50</cargo>
  <absorb>30</absorb>
  <armour>2500</armour>
  <armour_regen>0</armour_regen>
  <ew_hide>0</ew_hide>
 </specific>
</outfit>
