<outfit name="Previous Generation Large Systems">
 <general>
  <typename>Core Systems (System)</typename>
  <slot prop_extra="systems_secondary" prop="systems">utility</slot>
  <size>large</size>
  <price>0</price>
  <description>A jury-rigged mess of processors and generators that most captains wouldn't be seen dead having installed on their ship.</description>
  <gfx_store>misc02</gfx_store>
 </general>
 <specific type="modification">
  <lua_inline>
require("outfits.lib.multicore").init{
   { "mass", 1450, 1450},
   { "cpu_max", 145, 0},
   { "shield", 500, 0},
   { "shield_regen", 8, 0},
   { "energy", 1900, 0},
   { "energy_regen", 85, 0},
   { "ew_hide", 0, 0},
}</lua_inline>
 </specific>
</outfit>
