<ssys name="Allous">
 <general>
  <radius>10000</radius>
  <spacedust>400</spacedust>
  <interference>0</interference>
 </general>
 <pos x="634.562533" y="-840.093087"/>
 <spobs>
  <spob>Allous Citadel</spob>
  <spob>Allous GG-3</spob>
  <spob>Allous I</spob>
  <spob>Allous II</spob>
  <spob>Nanek</spob>
 </spobs>
 <jumps>
  <jump target="Faust">
   <hide>1</hide>
   <pos x="-8056.416759" y="-5924.031482" was_auto="true"/>
  </jump>
  <jump target="Palin">
   <hide>1</hide>
   <pos x="2365.23004" y="9716.258891" was_auto="true"/>
  </jump>
  <jump target="Suk">
   <hide>1</hide>
   <pos x="-9960.182946" y="891.490698" was_auto="true"/>
  </jump>
 </jumps>
</ssys>
