<ssys name="Paradox">
 <general>
  <radius>20000</radius>
  <spacedust>400</spacedust>
  <interference>0</interference>
 </general>
 <pos x="-1075.886454" y="175.152313"/>
 <spobs>
  <spob>Paradox II</spob>
  <spob>Paradox III</spob>
  <spob>Paradox III-a</spob>
  <spob>Paradox V</spob>
  <spob>Rockhardt</spob>
  <spob>Stella</spob>
 </spobs>
 <jumps>
  <jump target="Knave">
   <hide>1</hide>
   <pos x="-16851.956116" y="-10770.866958" was_auto="true"/>
  </jump>
  <jump target="NGC-11718">
   <hide>1</hide>
   <pos x="-7964.057469" y="18345.947471" was_auto="true"/>
  </jump>
  <jump target="Zemur">
   <hide>1</hide>
   <pos x="19712.681465" y="-3377.897194" was_auto="true"/>
  </jump>
 </jumps>
 <asteroids>
  <asteroid>
   <group>typeA-poor</group>
   <radius>2500</radius>
   <pos x="-2680.804884" y="-877.710992"/>
  </asteroid>
  <exclusion>
   <radius>1700</radius>
   <pos x="-2495.937495" y="1340.410877"/>
  </exclusion>
 </asteroids>
</ssys>
