<?xml version='1.0' encoding='UTF-8'?>
<ship name="Gawain">
 <points>20</points>
 <base_type>Gawain</base_type>
 <gfx size="56">gawain</gfx>
 <sound>engine</sound>
 <class display="Luxury Yacht">Yacht</class>
 <price>500000</price>
 <time_mod>0.9</time_mod>
 <trail_generator x="-2" y="15" h="-2">nebula</trail_generator>
 <trail_generator x="-2" y="-15" h="-2">nebula</trail_generator>
 <trail_generator x="-15" y="0" h="0" />
 <fabricator>Nexus Shipyards</fabricator>
 <description>The Gawain is a very high-end ship, outpacing nearly all other production vessels. It relies heavily on technology first implemented on the Lancelot and is widely used as a sporting vessel as it is extremely manoeuvrable, though they rarely survive combat due to their meagre weapons space and relative fragility.</description>
 <health>
  <armour>40</armour>
  <armour_regen>0</armour_regen>
 </health>
 <characteristics>
  <crew>2</crew>
  <mass>50</mass>
  <fuel_consumption>100</fuel_consumption>
  <cargo>10</cargo>
 </characteristics>
 <slots>
  <weapon size="small" x="12" y="0" h="-2" />
  <weapon size="small" x="-5" y="0" h="1" />
  <utility size="small" prop="systems">Unicorp PT-16 Core System</utility>
  <utility size="small" prop="accessory" />
  <utility size="small" />
  <utility size="small" />
  <utility size="small" />
  <utility size="small" />
  <structure size="small" prop="engines">Nexus Dart 160 Engine</structure>
  <structure size="small" prop="hull">Unicorp D-2 Light Plating</structure>
  <structure size="small" />
  <structure size="small" />
 </slots>
 <stats>
  <speed_mod>15</speed_mod>
  <turn_mod>10</turn_mod>
  <accel_mod>10</accel_mod>
  <cargo_mod>-10</cargo_mod>
  <armour_mod>-10</armour_mod>
  <land_delay>-20</land_delay>
 </stats>
 <tags>
  <tag>standard</tag>
  <tag>transport</tag>
  <tag>luxury</tag>
 </tags>
</ship>
