<outfit name="Kratos' Glove">
 <general>
  <rarity>1</rarity>
  <typename>System Improvement</typename>
  <slot>utility</slot>
  <size>small</size>
  <mass>1</mass>
  <price>135000</price>
  <description>A module that lets the ship's generator direct energy to its weapons in larger, more spaced out bursts. It's not perfectly efficient, but has been proven useful in some combat encounters.</description>
  <gfx_store>placeholder.webp</gfx_store>
 </general>
 <specific type="modification">
  <weapon_damage>20</weapon_damage>
  <energy_regen_mod>-5</energy_regen_mod>
  <weapon_firerate>-20</weapon_firerate>
 </specific>
</outfit>
